{
  "meta": {
    "id": "detected-white-vs-1-d6",
    "name": "[detected] White vs 1...d6",
    "side": "white",
    "rootFen": "rnbqkbnr/ppp1pppp/3p4/8/4P3/8/PPPP1PPP/RNBQKBNR w KQkq -",
    "description": "Your e4 repertoire against d6. Detected from 12 rapid/classical games.",
    "createdAt": "2026-04-18T22:15:50.779Z",
    "updatedAt": "2026-04-18T22:15:50.779Z"
  },
  "positions": {
    "rnbqkbnr/ppp1pppp/3p4/8/4P3/8/PPPP1PPP/RNBQKBNR w KQkq -": {
      "moves": [
        "d4"
      ],
      "notes": "",
      "nag": null,
      "eval": null
    },
    "rnbqkbnr/ppp1pppp/3p4/8/3PP3/8/PPP2PPP/RNBQKBNR b KQkq -": {
      "moves": [
        "Nf6"
      ],
      "notes": "",
      "nag": null,
      "eval": null
    },
    "rnbqkb1r/ppp1pppp/3p1n2/8/3PP3/8/PPP2PPP/RNBQKBNR w KQkq -": {
      "moves": [
        "Nc3"
      ],
      "notes": "",
      "nag": null,
      "eval": null
    },
    "rnbqkb1r/ppp1pppp/3p1n2/8/3PP3/2N5/PPP2PPP/R1BQKBNR b KQkq -": {
      "moves": [
        "g6"
      ],
      "notes": "",
      "nag": null,
      "eval": null
    }
  }
}